rko_2026_mcp_proxy/__init__.py
rko_2026_mcp_proxy/__main__.py
rko_2026_mcp_proxy-0.1.0.dist-info/licenses/LICENSE
rko_2026_mcp_proxy-0.1.0.dist-info/METADATA
rko_2026_mcp_proxy-0.1.0.dist-info/WHEEL
rko_2026_mcp_proxy-0.1.0.dist-info/entry_points.txt
rko_2026_mcp_proxy-0.1.0.dist-info/top_level.txt
rko_2026_mcp_proxy-0.1.0.dist-info/RECORD
