Metadata-Version: 2.4
Name: rko-2026-mcp-proxy
Version: 0.1.0
Summary: Add your description here
Requires-Python: >=3.10
License-File: LICENSE
Requires-Dist: fastmcp
Dynamic: license-file
